tiny_progress_bar/__init__.py
tiny_progress_bar/tiny_progress_bar.py
tiny_progress_bar-0.1.6.dist-info/LICENSE
tiny_progress_bar-0.1.6.dist-info/METADATA
tiny_progress_bar-0.1.6.dist-info/WHEEL
tiny_progress_bar-0.1.6.dist-info/top_level.txt
tiny_progress_bar-0.1.6.dist-info/RECORD
